mosaic/__init__.py
mosaic/attention.py
mosaic/benchmark.py
mosaic/context.py
mosaic/hierarchical.py
mosaic/spec.py
mosaic/backends/__init__.py
mosaic/backends/composed.py
mosaic/backends/local.py
mosaic/backends/mesh2d.py
mosaic/backends/mesh3d.py
mosaic/backends/ring.py
mosaic/examples/__init__.py
mosaic/examples/nanotabpfn.py
mosaic/integrations/__init__.py
mosaic/integrations/huggingface.py
mosaic/tests/__init__.py
mosaic/tests/test_attention.py
mosaic/tests/test_context.py
mosaic/tests/test_hierarchical.py
mosaic_attention-0.3.0.dist-info/METADATA
mosaic_attention-0.3.0.dist-info/WHEEL
mosaic_attention-0.3.0.dist-info/top_level.txt
mosaic_attention-0.3.0.dist-info/RECORD
