Metadata-Version: 2.4
Name: mosaic-attention
Version: 0.3.0
Summary: Multi-Axis Attention Sharding for PyTorch - Distribute attention across GPUs
Author-email: Pranav Sateesh <stprnvsh@example.com>
License: MIT
Project-URL: Homepage, https://github.com/stprnvsh/mosaic
Project-URL: Repository, https://github.com/stprnvsh/mosaic
Project-URL: Documentation, https://github.com/stprnvsh/mosaic#readme
Keywords: pytorch,attention,distributed,multi-gpu,transformer,ring-attention,sequence-parallel
Classifier: Development Status :: 4 - Beta
Classifier: Intended Audience :: Developers
Classifier: Intended Audience :: Science/Research
Classifier: License :: OSI Approved :: MIT License
Classifier: Programming Language :: Python :: 3
Classifier: Programming Language :: Python :: 3.9
Classifier: Programming Language :: Python :: 3.10
Classifier: Programming Language :: Python :: 3.11
Classifier: Programming Language :: Python :: 3.12
Classifier: Topic :: Scientific/Engineering :: Artificial Intelligence
Requires-Python: >=3.9
Requires-Dist: torch>=2.0.0
Provides-Extra: ring
Requires-Dist: flash-attn>=2.0.0; extra == "ring"
Provides-Extra: dev
Requires-Dist: pytest>=7.0.0; extra == "dev"
Requires-Dist: build; extra == "dev"
Requires-Dist: twine; extra == "dev"
Provides-Extra: all
Requires-Dist: flash-attn>=2.0.0; extra == "all"
